synlink-0.0.0.dev0.dist-info/METADATA
synlink-0.0.0.dev0.dist-info/WHEEL
synlink/__init__.py
synlink/_synlink_rs.abi3.so
synlink/error/__init__.ipy
synlink/error/__init__.py
synlink-0.0.0.dev0.dist-info/RECORD
