Metadata-Version: 2.4
Name: synlink
Version: 0.0.0.dev0
Classifier: Programming Language :: Rust
Classifier: Programming Language :: Python :: Implementation :: CPython
Classifier: Programming Language :: Python :: Implementation :: PyPy
Classifier: Intended Audience :: Developers
Classifier: Intended Audience :: Education
Classifier: Programming Language :: Python :: 3.8
Classifier: Programming Language :: Python :: 3.9
Classifier: Programming Language :: Python :: 3.10
Classifier: Typing :: Typed
Requires-Dist: black==22.3 ; extra == 'quality'
Requires-Dist: click==8.0.4 ; extra == 'quality'
Requires-Dist: isort>=5.5.4 ; extra == 'quality'
Requires-Dist: flake8>=3.8.3 ; extra == 'quality'
Requires-Dist: pytest>=7.2.0 ; extra == 'testing'
Requires-Dist: pytest-benchmark>=4.0.0 ; extra == 'testing'
Requires-Dist: hypothesis>=6.70.2 ; extra == 'testing'
Requires-Dist: synlink[testing] ; extra == 'fuzzing'
Requires-Dist: atheris>=2.3.0 ; extra == 'fuzzing'
Provides-Extra: quality
Provides-Extra: testing
Provides-Extra: fuzzing
Author-email: Luca Vivona <lucavivona01@gmail.com>
Requires-Python: >=3.8
